rolex/__init__.py
rolex/__init__.pyc
rolex/generator.py
rolex/generator.pyc
rolex/math.py
rolex/math.pyc
rolex/parse.py
rolex/parse.pyc
rolex/tz.py
rolex/tz.pyc
rolex/util.py
rolex/util.pyc
rolex/__pycache__/__init__.cpython-36.pyc
rolex/__pycache__/generator.cpython-36.pyc
rolex/__pycache__/math.cpython-36.pyc
rolex/__pycache__/parse.cpython-36.pyc
rolex/__pycache__/tz.cpython-36.pyc
rolex/__pycache__/util.cpython-36.pyc
rolex/pkg/__init__.py
rolex/pkg/__init__.pyc
rolex/pkg/sixmini.py
rolex/pkg/sixmini.pyc
rolex/pkg/__pycache__/__init__.cpython-36.pyc
rolex/pkg/__pycache__/sixmini.cpython-36.pyc
rolex-0.0.8.dist-info/AUTHORS.rst
rolex-0.0.8.dist-info/LICENSE.txt
rolex-0.0.8.dist-info/METADATA
rolex-0.0.8.dist-info/WHEEL
rolex-0.0.8.dist-info/top_level.txt
rolex-0.0.8.dist-info/RECORD
